[
  {"title":"CSS Architecture for Multi-Page Sites","url":"https://www.smashingmagazine.com/2016/06/strategies-organic-css-architecture/","type":"article","description":"Strategies for organizing CSS across pages."},
  {"title":"ITCSS Architecture","url":"https://www.xfive.co/blog/itcss-scalable-maintainable-css-architecture/","type":"article","description":"Scalable CSS architecture for large projects."},
  {"title":"ARIA Current Page","url":"https://developer.mozilla.org/en-US/docs/Web/Accessibility/ARIA/Attributes/aria-current","type":"documentation","description":"MDN guide to aria-current for navigation."},
  {"title":"Design Systems 101","url":"https://www.designsystems.com/","type":"article","description":"Guide to building and maintaining design systems."}
]
