{
  "videos": [
    {
      "title": "HTML Quotations - Web Dev Simplified",
      "url": "https://www.youtube.com/embed/NeisBGjPdlE",
      "channel": "Web Dev Simplified",
      "description": "Learn how to use HTML quotation and citation elements including q, blockquote, cite, and abbr elements."
    },
    {
      "title": "HTML Crash Course - Quotations & Citations",
      "url": "https://www.youtube.com/embed/UB1O30fR-EE",
      "channel": "Traversy Media",
      "description": "Brad Traversy covers HTML quotation elements, citations, abbreviations, and address elements."
    },
    {
      "title": "Semantic HTML: Quotes and Citations - Kevin Powell",
      "url": "https://www.youtube.com/embed/NKjW6AD2GD8",
      "channel": "Kevin Powell",
      "description": "Kevin Powell explains the importance of semantic quotation and citation elements for web accessibility."
    },
    {
      "title": "HTML Abbreviations and Acronyms",
      "url": "https://www.youtube.com/embed/8dQ1TdC7AxU",
      "channel": "Web Dev Simplified",
      "description": "A guide to using the HTML abbr element with title attributes for accessibility and SEO."
    },
    {
      "title": "HTML Address Element - Contact Information",
      "url": "https://www.youtube.com/embed/mJgBO1GAV9w",
      "channel": "freeCodeCamp.org",
      "description": "Learn how to properly mark up contact information using the HTML address element."
    }
  ]
}
