[
  {"question":"Which HTML element defines the page title?","options":["<head>","<title>","<meta>","<h1>"],"answer":"b","explanation":"The <title> element, placed inside <head>, defines the page title."},
  {"question":"Where does the page title appear in a browser?","options":["In the body of the page","In the browser tab","In the footer","In the sidebar"],"answer":"b","explanation":"The title appears in the browser tab, search results, bookmarks, and browser history."},
  {"question":"Is the <title> element required in HTML?","options":["Yes, it's required for valid HTML","No, it's optional","Only for SEO","Only for accessibility"],"answer":"a","explanation":"The <title> element is required for valid HTML documents. HTML validators will flag missing titles."},
  {"question":"What is the recommended character length for SEO titles?","options":["30-40 characters","50-60 characters","70-80 characters","100-120 characters"],"answer":"b","explanation":"Google typically displays 50-60 characters (about 600px). Longer titles get truncated with an ellipsis."},
  {"question":"Where must the <title> element be placed in an HTML document?","options":["Inside <body>","Inside <head>","Inside <footer>","Inside <main>"],"answer":"b","explanation":"The <title> element must be placed inside the <head> section of the HTML document."},
  {"question":"How do you change the page title dynamically with JavaScript?","options":["title.textContent","document.title","window.title","page.title"],"answer":"b","explanation":"document.title = 'New Title' changes the page title dynamically using JavaScript."},
  {"question":"What happens when a page doesn't have a <title> element?","options":["The page won't load","The browser shows 'Untitled' or the filename","The browser shows an error","The page redirects to the homepage"],"answer":"b","explanation":"Without a <title>, browsers typically display 'Untitled' or the page's filename in the tab."},
  {"question":"Which of these is a well-written page title?","options":["Home","How to Center a Div — CSS Tutorial | SiteName","Article 42","Page 1"],"answer":"b","explanation":"A good title is descriptive, includes keywords, and mentions the brand. 'How to Center a Div — CSS Tutorial | SiteName' follows best practices."},
  {"question":"What is keyword stuffing in titles?","options":["Using one keyword","Repeating keywords excessively for SEO","Using no keywords","Using keywords in the URL"],"answer":"b","explanation":"Keyword stuffing is the practice of cramming excessive keywords into a title, which search engines penalize."},
  {"question":"What should the title of a 404 error page be?","options":["404","Page Not Found — SiteName","Error","404: Page Not Found — SiteName"],"answer":"d","explanation":"A good 404 title clearly indicates the error while maintaining brand presence: '404: Page Not Found — SiteName'."},
  {"question":"Can you use HTML tags inside the <title> element?","options":["Yes, all HTML tags work","No, only text content is allowed","Only <strong> and <em>","Only <span>"],"answer":"b","explanation":"The <title> element can only contain plain text. HTML tags inside it will be displayed as literal text."},
  {"question":"What is the best title format for a blog article?","options":["Blog Post 42","Article Title — Site Name","Just the article title without brand","Site Name — Article Title"],"answer":"b","explanation":"Article Title — Site Name places the specific content first (important for SEO) and the brand last."},
  {"question":"How do search engines use page titles?","options":["They ignore titles","Titles are the clickable headline in search results","Titles determine page speed","Titles control page ranking entirely"],"answer":"b","explanation":"Search engines display the page title as the clickable headline in search results. It's a key ranking factor."},
  {"question":"Why should each page have a unique title?","options":["It's not necessary","For SEO and user identification","It makes the site load faster","It reduces server load"],"answer":"b","explanation":"Unique titles help search engines understand page differentiation and help users identify which page they're on."},
  {"question":"What is a 'title separator' commonly used between content and brand?","options":["— (em dash)","| (pipe)","- (hyphen)","All of the above are acceptable"],"answer":"d","explanation":"Em dashes, pipes, and hyphens are all acceptable title separators. The key is consistency across the site."},
  {"question":"What is the first thing a screen reader announces when loading a page?","options":["The main heading","The page title","The navigation","The first paragraph"],"answer":"b","explanation":"Screen readers announce the page title first, making it critical for accessibility."},
  {"question":"If your site is called 'MySite' and the article is '10 CSS Tips', what is the best title?","options":["MySite — 10 CSS Tips","10 CSS Tips — MySite","MySite Article","10 CSS Tips"],"answer":"b","explanation":"The article title should come first for SEO, with the brand at the end: '10 CSS Tips — MySite'."},
  {"question":"What happens if a title is longer than 60 characters in Google search results?","options":["It displays fully","It gets truncated with an ellipsis","It doesn't appear","Google ignores it"],"answer":"b","explanation":"Google truncates titles that are longer than ~60 characters (600px), adding an ellipsis at the end."},
  {"question":"How can you update a title when a user receives a new message in a web app?","options":["Reload the page","Use document.title to set a notification count","The user can't be notified","Use the <title> attribute"],"answer":"b","explanation":"document.title = '(3) New Messages' dynamically updates the title to show notifications."},
  {"question":"What should you avoid in page titles?","options":["Keywords","Brand name","Special characters excessively","Descriptive text"],"answer":"c","explanation":"Excessive special characters can cause display issues in browser tabs and search results."}
]
