[
  {
    "title": "A flexbox trick to improve text wrapping",
    "url": "https://www.youtube.com/watch?v=3ugXM3ZDUuE",
    "channel": "Kevin Powell",
    "duration": "5:01",
    "description": "Kevin Powell explains flex-wrap behavior and a common wrapping issue with practical solutions using min-width",
    "level": "beginner"
  },
  {
    "title": "Learn flexbox the easy way",
    "url": "https://www.youtube.com/watch?v=u044iM9xsWU",
    "channel": "Kevin Powell",
    "duration": "34:04",
    "description": "Kevin Powell covers how flex-wrap affects item behavior and creating multi-line flex containers",
    "level": "beginner"
  },
  {
    "title": "Learn Flexbox in 15 Minutes",
    "url": "https://www.youtube.com/watch?v=fYq5PXgSsbE",
    "channel": "Web Dev Simplified",
    "duration": "15:12",
    "description": "Kyle from Web Dev Simplified covers flex-wrap and creating responsive layouts that wrap to multiple rows",
    "level": "beginner"
  },
  {
    "title": "Flexbox Crash Course",
    "url": "https://www.youtube.com/watch?v=3YW65K6LcIA",
    "channel": "Traversy Media",
    "duration": "46:53",
    "description": "Brad Traversy explains flex-wrap with practical demonstrations of wrap, nowrap, and wrap-reverse values",
    "level": "beginner"
  }
]
