{
  "module": "CSS Float",
  "resources": [
    {
      "type": "article",
      "title": "MDN Web Docs: float",
      "url": "https://developer.mozilla.org/en-US/docs/Web/CSS/float",
      "description": "Official documentation with examples and browser compatibility",
      "difficulty": "beginner"
    },
    {
      "type": "article",
      "title": "CSS-Tricks: float",
      "url": "https://css-tricks.com/almanac/properties/f/float/",
      "description": "Practical guide to float with visual examples and use cases",
      "difficulty": "beginner"
    },
    {
      "type": "article",
      "title": "All About Floats",
      "url": "https://css-tricks.com/all-about-floats/",
      "description": "CSS-Tricks comprehensive guide to CSS floats",
      "difficulty": "beginner"
    },
    {
      "type": "video",
      "title": "Learn CSS Float in 10 Minutes",
      "url": "https://www.youtube.com/watch?v=2dHhMq4E2LQ",
      "channel": "Web Dev Simplified",
      "description": "Quick and practical guide to CSS floats",
      "difficulty": "beginner"
    },
    {
      "type": "video",
      "title": "CSS Float and Clear Explained",
      "url": "https://www.youtube.com/watch?v=EFvckxXNDZA",
      "channel": "Kevin Powell",
      "description": "Clear explanation of float and clear with examples",
      "difficulty": "beginner"
    },
    {
      "type": "video",
      "title": "CSS Float Tutorial - Learn CSS For Beginners",
      "url": "https://www.youtube.com/watch?v=2JLiGq1JFn8",
      "channel": "Programming with Mosh",
      "description": "Comprehensive beginner tutorial on CSS float",
      "difficulty": "beginner"
    },
    {
      "type": "article",
      "title": "The History of CSS Floats",
      "url": "https://www.smashingmagazine.com/2018/10/float-history-css/",
      "description": "Smashing Magazine article on the history and evolution of CSS floats",
      "difficulty": "intermediate"
    },
    {
      "type": "interactive",
      "title": "CSS Float Generator",
      "url": "https://cssgenerator.org/float-css-generator.html",
      "description": "Interactive tool to generate CSS float code",
      "difficulty": "beginner"
    }
  ]
}